LICENSE
mounty/__init__.py
mounty/errors.py
mounty/models.py
mounty/mountebank.py
mounty-1.0.2.dist-info/LICENSE
mounty-1.0.2.dist-info/WHEEL
mounty-1.0.2.dist-info/METADATA
mounty-1.0.2.dist-info/RECORD
