Metadata-Version: 2.1
Name: mounty
Version: 1.0.2
Summary: A simple Python client for Mountebank
Home-page: https://github.com/vicusbass/mounty
License: BSD 3
Keywords: mountebank,stub,testing
Author: Vasile Pop
Author-email: vasile.pop@gmail.com
Requires-Python: >=3.9,<4.0
Classifier: Development Status :: 4 - Beta
Classifier: Environment :: Web Environment
Classifier: Intended Audience :: Developers
Classifier: License :: OSI Approved :: BSD License
Classifier: License :: Other/Proprietary License
Classifier: Operating System :: OS Independent
Classifier: Programming Language :: Python :: 3
Classifier: Programming Language :: Python :: 3 :: Only
Classifier: Programming Language :: Python :: 3.10
Classifier: Programming Language :: Python :: 3.8
Classifier: Programming Language :: Python :: 3.9
Classifier: Topic :: Internet :: WWW/HTTP
Requires-Dist: requests (>=2.27.1,<3.0.0)
Project-URL: Repository, https://github.com/vicusbass/mounty
